[{"kind":"batsman","name":"Rishabh Pant","order_of_match":"Final (N)","venue":"Dubai","date":"Nov 10 2020","run":"56","ballfaced":"38","fours":"4","sixes":"2","run_rate":"147.37"},{"kind":"batsman","name":"Rishabh Pant","order_of_match":"47th Match (N)","venue":"Dubai","date":"Oct 27 2020","run":"36","ballfaced":"35","fours":"3","sixes":"1","run_rate":"102.86"},{"kind":"batsman","name":"Rishabh Pant","order_of_match":"38th Match (N)","venue":"Dubai","date":"Oct 20 2020","run":"14","ballfaced":"20","fours":"1","sixes":"0","run_rate":"70.00"},{"kind":"batsman","name":"Rishabh Pant","order_of_match":"16th Match (N)","venue":"Sharjah","date":"Oct 3 2020","run":"38","ballfaced":"17","fours":"5","sixes":"1","run_rate":"223.53"},{"kind":"batsman","name":"Rishabh Pant","order_of_match":"Qualifier 2 (N)","venue":"Abu Dhabi","date":"Nov 8 2020","run":"2","ballfaced":"3","fours":"0","sixes":"0","run_rate":"66.67"},{"kind":"batsman","name":"Rishabh Pant","order_of_match":"51st Match","venue":"Dubai","date":"Oct 31 2020","run":"21","ballfaced":"24","fours":"2","sixes":"0","run_rate":"87.50"},{"kind":"batsman","name":"Rishabh Pant","order_of_match":"Qualifier 1 (N)","venue":"Dubai","date":"Nov 5 2020","run":"3","ballfaced":"9","fours":"0","sixes":"0","run_rate":"33.33"},{"kind":"batsman","name":"Rishabh Pant","order_of_match":"42nd Match","venue":"Abu Dhabi","date":"Oct 24 2020","run":"27","ballfaced":"33","fours":"2","sixes":"1","run_rate":"81.82"},{"kind":"batsman","name":"Rishabh Pant","order_of_match":"2nd Match (N)","venue":"Dubai","date":"Sep 20 2020","run":"31","ballfaced":"29","fours":"4","sixes":"0","run_rate":"106.90"},{"kind":"batsman","name":"Rishabh Pant","order_of_match":"19th Match (N)","venue":"Dubai","date":"Oct 5 2020","run":"37","ballfaced":"25","fours":"3","sixes":"2","run_rate":"148.00"},{"kind":"batsman","name":"Rishabh Pant","order_of_match":"7th Match (N)","venue":"Dubai","date":"Sep 25 2020","run":"37","ballfaced":"25","fours":"5","sixes":"0","run_rate":"148.00"},{"kind":"batsman","name":"Rishabh Pant","order_of_match":"11th Match (N)","venue":"Abu Dhabi","date":"Sep 29 2020","run":"28","ballfaced":"27","fours":"1","sixes":"2","run_rate":"103.70"},{"kind":"batsman","name":"Rishabh Pant","order_of_match":"55th Match (N)","venue":"Abu Dhabi","date":"Nov 2 2020","run":"8","ballfaced":"7","fours":"1","sixes":"0","run_rate":"114.29"},{"kind":"batsman","name":"Rishabh Pant","order_of_match":"23rd Match (N)","venue":"Sharjah","date":"Oct 9 2020","run":"5","ballfaced":"9","fours":"0","sixes":"0","run_rate":"55.56"}]